{
  "name": "tailscale",
  "version": 1,
  "description": "Secure remote access to your NAS",
  "services": {
    "tailscale": {
      "container_name": "${TAILSCALE_CONTAINER_NAME}",
      "image": "${TAILSCALE_IMAGE}",
      "network_mode": "${TAILSCALE_NETWORK_MODE}",
      "restart": "${RESTART_POLICY}",
      "environment": {
        "TS_AUTHKEY": "${TS_AUTHKEY}",
        "TS_HOSTNAME": "${TS_HOSTNAME}",
        "TS_ACCEPT_DNS": "${TS_ACCEPT_DNS}",
        "TS_AUTH_ONCE": "${TS_AUTH_ONCE}",
        "TS_ROUTES": "${TS_ROUTES}",
        "TS_EXTRA_ARGS": "${EXIT_NODE_EXTRA_ARGS} ${TS_EXTRA_ARGS}",
        "TS_TAILSCALED_EXTRA_ARGS": "${TS_TAILSCALED_EXTRA_ARGS}",
        "TS_USERSPACE": "${TS_USERSPACE}",
        "TS_STATE_DIR": "${TS_STATE_DIR}"
      },
      "command": "${TAILSCALE_COMMAND}",
      "entrypoint": "${TAILSCALE_ENTRYPOINT}",
      "volumes": [
        "${TAILSCALE_DATA_LOCATION}:${TS_STATE_DIR}"
      ],
      "cap_add": [
        "${TAILSCALE_CAP_ADD_NET_ADMIN}",
        "${TAILSCALE_CAP_ADD_NET_RAW}"
      ],
      "devices": [
        "${TAILSCALE_TUN_DEVICE}"
      ]
    }
  },
  "fields": [
    {
      "name": "TS_AUTHKEY",
      "label": "Auth Key",
      "section": "required",
      "input_type": "password",
      "required": true,
      "default": "",
      "help": "Visit <a href=\"https://login.tailscale.com/admin/settings/keys\" target=\"_blank\" rel=\"noopener noreferrer\">the Tailscale auth keys page</a>, generate a key, and paste it here."
    },
    {
      "name": "TAILSCALE_DATA_LOCATION",
      "label": "Tailscale Data Folder",
      "section": "required",
      "input_type": "text",
      "required": true,
      "default": "./tailscale_data",
      "help": "Stores persistent Tailscale state so the container can reconnect after restart."
    },
    {
      "name": "TS_HOSTNAME",
      "label": "Advertised Hostname",
      "section": "optional",
      "input_type": "text",
      "required": false,
      "default": "",
      "help": "Name you want to give this device in Tailscale.<br>Example: <code>UgreenDXP</code> or <code>MediaNAS</code>."
    },
    {
      "name": "RESTART_POLICY",
      "label": "Restart Policy",
      "section": "optional",
      "input_type": "select",
      "required": true,
      "default": "unless-stopped",
      "options": [
        {
          "label": "Unless Stopped",
          "value": "unless-stopped"
        },
        {
          "label": "Always",
          "value": "always"
        },
        {
          "label": "On Failure",
          "value": "on-failure"
        },
        {
          "label": "No",
          "value": "no"
        }
      ],
      "help": "Controls whether the container restarts automatically after reboot."
    },
    {
      "name": "EXIT_NODE_EXTRA_ARGS",
      "label": "Advertise as Exit Node",
      "section": "optional",
      "input_type": "select",
      "required": false,
      "default": "",
      "options": [
        {
          "label": "No",
          "value": ""
        },
        {
          "label": "Yes",
          "value": "--advertise-exit-node"
        }
      ],
      "help": "Routes all internet traffic from selected devices through this NAS.<br>Requires approval in the Tailscale admin console."
    },
    {
      "name": "TS_ROUTES",
      "label": "Advertised Routes",
      "section": "optional",
      "input_type": "text",
      "required": false,
      "default": "",
      "help": "Optional subnet routes to advertise, comma-separated.<br>Example: <code>192.168.1.0/24,10.0.0.0/24</code>."
    },
    {
      "name": "TS_ACCEPT_DNS",
      "label": "Accept DNS",
      "section": "optional",
      "input_type": "select",
      "required": true,
      "default": "true",
      "options": [
        {
          "label": "Yes",
          "value": "true"
        },
        {
          "label": "No",
          "value": "false"
        }
      ],
      "help": "Use Tailscale DNS so MagicDNS names work on this device."
    },
    {
      "name": "TS_AUTH_ONCE",
      "label": "Auth Once",
      "section": "optional",
      "input_type": "select",
      "required": true,
      "default": "false",
      "options": [
        {
          "label": "No",
          "value": "false"
        },
        {
          "label": "Yes",
          "value": "true"
        }
      ],
      "help": "If enabled, the auth key is used only for the first login when state already exists."
    },
    {
      "name": "TS_EXTRA_ARGS",
      "label": "Extra tailscale up Arguments",
      "section": "advanced",
      "input_type": "textarea",
      "rows": 2,
      "required": false,
      "default": "",
      "help": "Optional extra arguments passed to <code>tailscale up</code>.<br>Example: <code>--accept-routes --advertise-tags=tag:nas</code>"
    },
    {
      "name": "TS_TAILSCALED_EXTRA_ARGS",
      "label": "Extra tailscaled Arguments",
      "section": "advanced",
      "input_type": "textarea",
      "rows": 2,
      "required": false,
      "default": "",
      "help": "Optional extra arguments passed to the <code>tailscaled</code> daemon."
    },
    {
      "name": "TS_USERSPACE",
      "label": "Userspace Networking",
      "section": "advanced",
      "input_type": "select",
      "required": true,
      "default": "false",
      "options": [
        {
          "label": "Disabled",
          "value": "false"
        },
        {
          "label": "Enabled",
          "value": "true"
        }
      ],
      "help": "Usually leave this disabled when <code>/dev/net/tun</code> is available."
    },
    {
      "name": "TAILSCALE_COMMAND",
      "label": "Compose Command Override",
      "section": "advanced",
      "input_type": "textarea",
      "data_type": "yaml",
      "rows": 2,
      "required": false,
      "default": "",
      "help": "Optional Docker Compose command override.<br>Can be a plain string or YAML list."
    },
    {
      "name": "TAILSCALE_ENTRYPOINT",
      "label": "Compose Entrypoint Override",
      "section": "advanced",
      "input_type": "textarea",
      "data_type": "yaml",
      "rows": 2,
      "required": false,
      "default": "",
      "help": "Optional Docker Compose entrypoint override.<br>Can be a plain string or YAML list."
    },
    {
      "name": "TAILSCALE_IMAGE",
      "label": "Image",
      "section": "advanced",
      "input_type": "text",
      "required": true,
      "default": "tailscale/tailscale:latest",
      "docs_url": "https://tailscale.com/kb/1282/docker",
      "docs_label": "Official help",
      "help": "Docker image used for Tailscale.<br>Change this only if you want a different tag or image source."
    },
    {
      "name": "TAILSCALE_CONTAINER_NAME",
      "label": "Container Name",
      "section": "readonly",
      "input_type": "text",
      "required": true,
      "default": "${PROJECT_NAME}",
      "editable": false,
      "help": "EasyDocker sets the container name from the project name."
    },
    {
      "name": "TAILSCALE_NETWORK_MODE",
      "label": "Network Mode",
      "section": "readonly",
      "input_type": "text",
      "required": true,
      "default": "host",
      "editable": false,
      "help": "Runs with host networking so Tailscale can manage routes directly."
    },
    {
      "name": "TS_STATE_DIR",
      "label": "State Directory Inside Container",
      "section": "readonly",
      "input_type": "text",
      "required": true,
      "default": "/var/lib/tailscale",
      "editable": false,
      "help": "Recipe-managed internal state directory used by the container."
    },
    {
      "name": "TAILSCALE_CAP_ADD_NET_ADMIN",
      "label": "Linux Capability: NET_ADMIN",
      "section": "readonly",
      "input_type": "text",
      "required": true,
      "default": "NET_ADMIN",
      "editable": false,
      "help": "Required capability for Tailscale networking operations."
    },
    {
      "name": "TAILSCALE_CAP_ADD_NET_RAW",
      "label": "Linux Capability: NET_RAW",
      "section": "readonly",
      "input_type": "text",
      "required": true,
      "default": "NET_RAW",
      "editable": false,
      "help": "Required capability for raw socket operations."
    },
    {
      "name": "TAILSCALE_TUN_DEVICE",
      "label": "TUN Device Mapping",
      "section": "readonly",
      "input_type": "text",
      "required": true,
      "default": "/dev/net/tun:/dev/net/tun",
      "editable": false,
      "help": "Provides access to the TUN device used by Tailscale."
    }
  ],
  "ui": {
    "sections": [
      {
        "name": "required",
        "label": "Minimum Required"
      },
      {
        "name": "optional",
        "label": "Optional",
        "collapsed": true
      },
      {
        "name": "advanced",
        "label": "Advanced",
        "collapsed": true
      },
      {
        "name": "readonly",
        "label": "Read-Only (Recipe Managed)",
        "collapsed": true
      }
    ],
    "tags": [
      "Intel/AMD",
      "ARM"
    ],
    "overview": "Tailscale gives your NAS secure remote access without exposing ports to the public internet.",
    "what_happens": [
      "A Tailscale container will be created",
      "It will run with host networking and access to /dev/net/tun",
      "Its persistent state will be saved in the folder you choose",
      "You can optionally advertise subnet routes or allow this device to become an exit node",
      "Advanced flags remain available when you need more control"
    ],
    "data_location": "Stored relative to this app's config folder unless you enter an absolute path."
  }
}
